odoo/addons/attachment_queue/README.rst
odoo/addons/attachment_queue/__init__.py
odoo/addons/attachment_queue/__manifest__.py
odoo/addons/attachment_queue/data/cron.xml
odoo/addons/attachment_queue/data/ir_config_parameter.xml
odoo/addons/attachment_queue/data/mail_template.xml
odoo/addons/attachment_queue/demo/attachment_queue_demo.xml
odoo/addons/attachment_queue/i18n/attachment_queue.pot
odoo/addons/attachment_queue/models/__init__.py
odoo/addons/attachment_queue/models/attachment_queue.py
odoo/addons/attachment_queue/readme/CONTRIBUTORS.rst
odoo/addons/attachment_queue/readme/DESCRIPTION.rst
odoo/addons/attachment_queue/readme/USAGE.rst
odoo/addons/attachment_queue/security/ir.model.access.csv
odoo/addons/attachment_queue/static/description/form.png
odoo/addons/attachment_queue/static/description/icon.png
odoo/addons/attachment_queue/static/description/index.html
odoo/addons/attachment_queue/static/description/tree.png
odoo/addons/attachment_queue/tests/__init__.py
odoo/addons/attachment_queue/tests/test_attachment_queue.py
odoo/addons/attachment_queue/views/attachment_queue_view.xml
odoo14_addon_attachment_queue-14.0.1.0.2.dist-info/METADATA
odoo14_addon_attachment_queue-14.0.1.0.2.dist-info/WHEEL
odoo14_addon_attachment_queue-14.0.1.0.2.dist-info/top_level.txt
odoo14_addon_attachment_queue-14.0.1.0.2.dist-info/RECORD
